cdklabs/cdk-amazonmq-activemq-config-v5-18-4/__init__.py
cdklabs/cdk-amazonmq-activemq-config-v5-18-4/py.typed
cdklabs/cdk-amazonmq-activemq-config-v5-18-4/_jsii/__init__.py
cdklabs/cdk-amazonmq-activemq-config-v5-18-4/_jsii/cdk-amazonmq-activemq-config-v5-18-4@0.0.0.jsii.tgz
cdklabs.cdk_amazonmq_activemq_config_v5_18_4-0.0.0.dist-info/LICENSE
cdklabs.cdk_amazonmq_activemq_config_v5_18_4-0.0.0.dist-info/METADATA
cdklabs.cdk_amazonmq_activemq_config_v5_18_4-0.0.0.dist-info/WHEEL
cdklabs.cdk_amazonmq_activemq_config_v5_18_4-0.0.0.dist-info/top_level.txt
cdklabs.cdk_amazonmq_activemq_config_v5_18_4-0.0.0.dist-info/RECORD
