Metadata-Version: 2.1
Name: cdklabs.cdk-amazonmq-activemq-config-v5-18-4
Version: 0.0.0
Summary: @cdklabs/cdk-amazonmq-activemq-config-v5-18-4
Home-page: https://github.com/cdklabs/cdk-amazonmq-activemq-configs
Author: AWS<cdk-amazonmq-maintainers@amazon.com>
License: Apache-2.0
Project-URL: Source, https://github.com/cdklabs/cdk-amazonmq-activemq-configs
Classifier: Intended Audience :: Developers
Classifier: Operating System :: OS Independent
Classifier: Programming Language :: JavaScript
Classifier: Programming Language :: Python :: 3 :: Only
Classifier: Programming Language :: Python :: 3.8
Classifier: Programming Language :: Python :: 3.9
Classifier: Programming Language :: Python :: 3.10
Classifier: Programming Language :: Python :: 3.11
Classifier: Typing :: Typed
Classifier: Development Status :: 4 - Beta
Classifier: License :: OSI Approved
Requires-Python: ~=3.8
License-File: LICENSE
Requires-Dist: jsii<2.0.0,>=1.106.0
Requires-Dist: publication>=0.0.3
Requires-Dist: typeguard<4.3.0,>=2.13.3
